mrphy/__init__.py
mrphy/beffective.py
mrphy/mobjs.py
mrphy/sims.py
mrphy/slowsims.py
mrphy/utils.py
mrphy/version.py
tests/__init__.py
tests/test_mobjs.py
tests/test_sims.py
tests/test_slowsims.py
tests/test_utils.py
mrphy-0.2.0.dist-info/LICENSE
mrphy-0.2.0.dist-info/METADATA
mrphy-0.2.0.dist-info/WHEEL
mrphy-0.2.0.dist-info/top_level.txt
mrphy-0.2.0.dist-info/RECORD
