Metadata-Version: 2.1
Name: mrphy
Version: 0.2.0
Summary: A Pytorch based tool for MR physics simulations
Home-page: https://github.com/tianrluo/MRphy.py
Author: Tianrui Luo
Author-email: tianrluo@umich.edu
License: MIT
Classifier: Programming Language :: Python :: 3
Classifier: License :: OSI Approved :: MIT License
Classifier: Operating System :: OS Independent
Requires-Python: >=3.8
License-File: LICENSE
Requires-Dist: torch (>=1.13)
Requires-Dist: numpy
Requires-Dist: scipy
